Metadata-Version: 2.1
Name: distrib-probab
Version: 0.1
Summary: Gaussian distributions
Home-page: UNKNOWN
Author: Stephen G
License: UNKNOWN
Platform: UNKNOWN
